CHANGES.rst
MANIFEST.in
README.rst
setup.cfg
setup.py
smartdc/__init__.py
smartdc/datacenter.py
smartdc/machine.py
smartdc.egg-info/PKG-INFO
smartdc.egg-info/SOURCES.txt
smartdc.egg-info/dependency_links.txt
smartdc.egg-info/requires.txt
smartdc.egg-info/top_level.txt
smartdc.egg-info/zip-safe