Metadata-Version: 1.0
Name: smartdc
Version: 0.1.6
Summary: Joyent SmartDataCenter CloudAPI connector using http-signature authentication via Requests
Home-page: https://github.com/atl/py-smartdc
Author: Adam T. Lindsay
Author-email: a.lindsay+github@gmail.com
License: MIT
Keywords: http,web,joyent,admin,operations
Platform: UNKNOWN
Classifier: Programming Language :: Python
Classifier: Topic :: Software Development :: Libraries :: Python Modules
Classifier: Topic :: System :: Boot
Classifier: Topic :: System :: Systems Administration
Classifier: Topic :: Internet :: WWW/HTTP :: Site Management
Classifier: Environment :: Web Environment
Classifier: Intended Audience :: Developers
Classifier: Intended Audience :: System Administrators
Classifier: License :: OSI Approved :: MIT License
Classifier: Development Status :: 3 - Alpha
